pyntbci/__init__.py
pyntbci/classifiers.py
pyntbci/envelope.py
pyntbci/gates.py
pyntbci/plotting.py
pyntbci/stimulus.py
pyntbci/stopping.py
pyntbci/transformers.py
pyntbci/utilities.py
pyntbci/capfiles/biosemi256.loc
pyntbci/capfiles/biosemi256.txt
pyntbci/capfiles/biosemi32.loc
pyntbci/capfiles/biosemi32.txt
pyntbci/capfiles/biosemi64.loc
pyntbci/capfiles/biosemi64.txt
pyntbci/capfiles/brainamp64.loc
pyntbci/capfiles/thielen8.loc
pyntbci/data/thielen2021_sub-01.npz
pyntbci/data/thielen2021_sub-02.npz
pyntbci/data/thielen2021_sub-03.npz
pyntbci/data/thielen2021_sub-04.npz
pyntbci/data/thielen2021_sub-05.npz
pyntbci/data/tutorial.npz
pyntbci/tests/__init__.py
pyntbci/tests/classifiers.py
pyntbci/tests/gates.py
pyntbci/tests/stimulus.py
pyntbci/tests/stopping.py
pyntbci/tests/transformers.py
pyntbci/tests/utilities.py
pyntbci-1.8.3.dist-info/licenses/LICENSE
pyntbci-1.8.3.dist-info/METADATA
pyntbci-1.8.3.dist-info/WHEEL
pyntbci-1.8.3.dist-info/top_level.txt
pyntbci-1.8.3.dist-info/RECORD
