Metadata-Version: 2.4
Name: pyntbci
Version: 1.8.3
Summary: Python Noise-Tagging Brain-Computer Interface (PyntBCI)
Home-page: https://github.com/thijor/pyntbci
Author: Jordy Thielen
Author-email: jordy.thielen@donders.ru.nl
License: BSD-3-Clause
Keywords: bci,classification,cvep,c-vep,eeg
Classifier: Development Status :: 4 - Beta
Classifier: Intended Audience :: Science/Research
Classifier: Intended Audience :: Developers
Classifier: License :: OSI Approved :: BSD License
Classifier: Operating System :: Microsoft :: Windows
Classifier: Operating System :: POSIX
Classifier: Operating System :: Unix
Classifier: Operating System :: MacOS
Classifier: Programming Language :: Python :: 3
Classifier: Programming Language :: Python :: 3.8
Classifier: Programming Language :: Python :: 3.9
Classifier: Programming Language :: Python :: 3.10
Classifier: Programming Language :: Python :: 3.11
Classifier: Programming Language :: Python :: 3.12
Classifier: Topic :: Scientific/Engineering :: Artificial Intelligence
Requires-Python: >=3.7
License-File: LICENSE
Requires-Dist: h5py>=3.10.0
Requires-Dist: matplotlib>=3.7.0
Requires-Dist: mne>=1.4.0
Requires-Dist: numpy>=1.24.0
Requires-Dist: scikit-learn>=1.3.0
Requires-Dist: scipy>=1.10.0
Requires-Dist: seaborn>=0.13.0
Requires-Dist: setuptools>=57.0.0
Dynamic: license-file
